{
    "437401144210227210": {
        "plan": "free"
    },
    "1009577884786098247": {
        "plan": "free"
    },
    "1037799236772835480": {
        "plan": "free"
    },
    "555158309720686596": {
        "plan": "free"
    },
    "937031277457080401": {
        "plan": "free"
    },
    "938492493195014255": {
        "plan": "medium"
    },
    "1058746345973878787": {
        "plan": "free"
    },
    "229811046586515456": {
        "plan": "free"
    },
    "1023044334301495336": {
        "plan": "free"
    }
}